{
  "project_info": {
    "project_number": "1002274650961",
    "firebase_url": "https://sinky-star.firebaseio.com",
    "project_id": "sinky-star",
    "storage_bucket": "sinky-star.appspot.com"
  },
  "client": [
    {
      "client_info": {
        "mobilesdk_app_id": "1:1002274650961:android:8224f498f0bac49c413170",
        "android_client_info": {
          "package_name": "com.joad.sinkystar"
        }
      },
      "oauth_client": [
        {
          "client_id": "1002274650961-ek95t6b1b5e4ggb9pl6ldeh3q03l9ctu.apps.googleusercontent.com",
          "client_type": 3
        }
      ],
      "api_key": [
        {
          "current_key": "AIzaSyBx6tkwK57Cs1_KWYbfCtZFshmySceHMfM"
        }
      ],
      "services": {
        "appinvite_service": {
          "other_platform_oauth_client": [
            {
              "client_id": "1002274650961-ek95t6b1b5e4ggb9pl6ldeh3q03l9ctu.apps.googleusercontent.com",
              "client_type": 3
            }
          ]
        }
      }
    }
  ],
  "configuration_version": "1"
}